tests/__init__.py
tests/test_lazy.py
turbo_lazy/__init__.py
turbo_lazy/views.py
turbo_lazy/migrations/__init__.py
turbo_lazy/templates/turbo_lazy/lazy_import.html
turbo_lazy/templates/turbo_lazy/turbo_frame.html
turbo_lazy/templatetags/__init__.py
turbo_lazy/templatetags/lazy.py
turbo_lazy/templatetags/partials.py
turbo_lazy-0.2.2.dist-info/LICENSE
turbo_lazy-0.2.2.dist-info/METADATA
turbo_lazy-0.2.2.dist-info/WHEEL
turbo_lazy-0.2.2.dist-info/top_level.txt
turbo_lazy-0.2.2.dist-info/RECORD
