Metadata-Version: 2.1
Name: turbo-lazy
Version: 0.2.2
Summary: Turbo-Frame based Lazy Loading
Home-page: https://github.com/hotwire-django/turbo-lazy
Author: Julian Feinauer
Author-email: j.feinauer@pragmaticminds.de
License: UNKNOWN
Keywords: turbo,hotwire,lazy
Platform: UNKNOWN
Classifier: Development Status :: 3 - Alpha
Classifier: Intended Audience :: Developers
Classifier: License :: OSI Approved :: MIT License
Classifier: Programming Language :: Python :: 3
Classifier: Programming Language :: Python :: 3.6
Classifier: Programming Language :: Python :: 3.7
Classifier: Programming Language :: Python :: 3.8
Classifier: Programming Language :: Python :: 3 :: Only
Requires-Python: >=3.6, <4
Requires-Dist: Django (>=3)
Requires-Dist: django-tag-parser (>=3.2)
